[{"level":"U","grade":"12","name":"Physics","students":[{"password":"sample_password","total":"0","incorrect":"0","studentNumber":"333333333","name":"Yili Liu"},{"password":"sample_password","total":"0","incorrect":"0","studentNumber":"333333333","name":"Yili Liu"}],"units":[{"number":"1","name":"TLAP","questions":[{"problem":"What is TLAP?","formula":" ( velocity + nuclearEnergy ) mul time "},{"problem":"What is TLAP?","formula":" ( velocity + nuclearEnergy ) mul time "}]}]},{"level":"AP","grade":"12","name":"Physics","students":[],"units":[{"number":"1","name":"Kinematics","questions":[]}]},{"level":"U","grade":"11","name":"Physics","students":[],"units":[]},{"level":"AP","grade":"11","name":"Physics","students":[],"units":[]}] 
